openmeteo_sdk/Aggregation.py
openmeteo_sdk/Aggregation.pyi
openmeteo_sdk/Model.py
openmeteo_sdk/Model.pyi
openmeteo_sdk/Unit.py
openmeteo_sdk/Unit.pyi
openmeteo_sdk/Variable.py
openmeteo_sdk/Variable.pyi
openmeteo_sdk/VariableWithValues.py
openmeteo_sdk/VariableWithValues.pyi
openmeteo_sdk/VariablesWithMonth.py
openmeteo_sdk/VariablesWithMonth.pyi
openmeteo_sdk/VariablesWithTime.py
openmeteo_sdk/VariablesWithTime.pyi
openmeteo_sdk/WeatherApiResponse.py
openmeteo_sdk/WeatherApiResponse.pyi
openmeteo_sdk/__init__.py
openmeteo_sdk-1.21.1.dist-info/METADATA
openmeteo_sdk-1.21.1.dist-info/WHEEL
openmeteo_sdk-1.21.1.dist-info/RECORD
